edc_lab_panel/__init__.py
edc_lab_panel/apps.py
edc_lab_panel/constants.py
edc_lab_panel/panels.py
edc_lab_panel/processing_profiles.py
edc_lab_panel/model_mixin_factory/__init__.py
edc_lab_panel/model_mixin_factory/field_attrs.py
edc_lab_panel/model_mixin_factory/reportable_result_model_mixin_factory.py
edc_lab_panel/model_mixin_factory/result_model_mixin_factory.py
edc_lab_panel/tests/__init__.py
edc_lab_panel/tests/test_settings.py
edc_lab_panel/tests/urls.py
edc_lab_panel/tests/etc/user-aes-local.key
edc_lab_panel/tests/etc/user-aes-restricted.key
edc_lab_panel/tests/etc/user-rsa-local-private.pem
edc_lab_panel/tests/etc/user-rsa-local-public.pem
edc_lab_panel/tests/etc/user-rsa-restricted-private.pem
edc_lab_panel/tests/etc/user-rsa-restricted-public.pem
edc_lab_panel/tests/etc/user-salt-local.key
edc_lab_panel/tests/etc/user-salt-restricted.key
edc_lab_panel/tests/tests/__init__.py
edc_lab_panel/tests/tests/test_field_attrs.py
edc_lab_panel-1.0.0.dist-info/AUTHORS
edc_lab_panel-1.0.0.dist-info/LICENSE
edc_lab_panel-1.0.0.dist-info/METADATA
edc_lab_panel-1.0.0.dist-info/WHEEL
edc_lab_panel-1.0.0.dist-info/top_level.txt
edc_lab_panel-1.0.0.dist-info/RECORD
